drb/drivers/eurostat/__init__.py
drb/drivers/eurostat/_version.py
drb/drivers/eurostat/eurostat.py
drb/topics/eurostat/__init__.py
drb/topics/eurostat/cortex.yml
drb_driver_eurostat-1.3.1.dist-info/LICENCE.txt
drb_driver_eurostat-1.3.1.dist-info/METADATA
drb_driver_eurostat-1.3.1.dist-info/WHEEL
drb_driver_eurostat-1.3.1.dist-info/entry_points.txt
drb_driver_eurostat-1.3.1.dist-info/top_level.txt
drb_driver_eurostat-1.3.1.dist-info/RECORD
