Metadata-Version: 2.1
Name: drb-driver-eurostat
Version: 1.3.1
Summary: DRB Eurostat Driver
Author: GAEL Systems
Author-email: drb-python@gael.fr
License: LGPLv3
Project-URL: Documentation, http://drb-python.gitlab.io/impl/eurostat
Project-URL: Source, https://gitlab.com/drb-python/impl/eurostat
Classifier: Programming Language :: Python :: 3.8
Classifier: Environment :: Plugins
Classifier: License :: OSI Approved :: GNU Lesser General Public License v3 (LGPLv3)
Requires-Python: >=3.8
License-File: LICENCE.txt
Requires-Dist: drb ~=2.2.0
Requires-Dist: eurostat ~=1.0.1
Requires-Dist: pandas >=2.0.1
